ext/__init__.py
ext/ios/__init__.py
ext/ios/ime.py
ext/ios/media.py
ext/ios/node.py
ext/ios/ui.py
ext/ios/action/__init__.py
ext/ios/screen/__init__.py
ext/ios/screen/image.py
ext/ios/screen/yolov8.py
ext/ios/system/__init__.py
ext/ios/system/device.py
kuaijs_ios_ext-0.2.40.dist-info/METADATA
kuaijs_ios_ext-0.2.40.dist-info/WHEEL
kuaijs_ios_ext-0.2.40.dist-info/top_level.txt
kuaijs_ios_ext-0.2.40.dist-info/RECORD
