Metadata-Version: 2.4
Name: kuaijs-ios-ext
Version: 0.2.40
Summary: 快点JS代码提示与类型检查。
Author: KuaiJS
License-Expression: MIT
Keywords: kuaijs,types,stubs,ios,automation
Classifier: Programming Language :: Python :: 3
Classifier: Operating System :: OS Independent
Requires-Python: >=3.8
